<?xml version='1.0' encoding='UTF-8'?>
<sch:DomainTable xmlns:sch="http://Baf.com/schemas" name="ProductContentType">
    <sch:name>ProductContentType</sch:name>
    <sch:domainType>LIST_OF_VALUES</sch:domainType>
    <sch:description></sch:description>
    <sch:domainKeys/>
    <sch:domainEntries>
        <sch:BmfDomainEntry>
            <sch:seqNumber>1</sch:seqNumber>
            <sch:displayValue>购买展示图片</sch:displayValue>
            <sch:dataValue>IMG</sch:dataValue>
            <sch:keyValues>{}</sch:keyValues>
        </sch:BmfDomainEntry>
        <sch:BmfDomainEntry>
            <sch:seqNumber>2</sch:seqNumber>
            <sch:displayValue>产品详情图片</sch:displayValue>
            <sch:dataValue>DETLIMG</sch:dataValue>
            <sch:keyValues>{}</sch:keyValues>
        </sch:BmfDomainEntry>
        <sch:BmfDomainEntry>
            <sch:seqNumber>3</sch:seqNumber>
            <sch:displayValue>产品条款</sch:displayValue>
            <sch:dataValue>DOC</sch:dataValue>
            <sch:keyValues>{}</sch:keyValues>
        </sch:BmfDomainEntry>
        <sch:BmfDomainEntry>
            <sch:seqNumber>4</sch:seqNumber>
            <sch:displayValue>购买协议</sch:displayValue>
            <sch:dataValue>PROTOCOL</sch:dataValue>
            <sch:keyValues>{}</sch:keyValues>
        </sch:BmfDomainEntry>
        <sch:BmfDomainEntry>
            <sch:seqNumber>5</sch:seqNumber>
            <sch:displayValue>交易详情推广图片</sch:displayValue>
            <sch:dataValue>EXTENDIMG</sch:dataValue>
            <sch:keyValues>{}</sch:keyValues>
        </sch:BmfDomainEntry>
        <sch:BmfDomainEntry>
            <sch:seqNumber>6</sch:seqNumber>
            <sch:displayValue>回访函</sch:displayValue>
            <sch:dataValue>FOLLOWUPDOC</sch:dataValue>
            <sch:keyValues>{}</sch:keyValues>
        </sch:BmfDomainEntry>
        <sch:BmfDomainEntry>
            <sch:seqNumber>7</sch:seqNumber>
            <sch:displayValue>服务协议</sch:displayValue>
            <sch:dataValue>SERVICEPROTOCOL</sch:dataValue>
            <sch:keyValues>{}</sch:keyValues>
        </sch:BmfDomainEntry>
        <sch:BmfDomainEntry>
            <sch:seqNumber>8</sch:seqNumber>
            <sch:displayValue>基金经理图片</sch:displayValue>
            <sch:dataValue>FUNDMANAGER</sch:dataValue>
            <sch:keyValues>{}</sch:keyValues>
        </sch:BmfDomainEntry>
        <sch:BmfDomainEntry>
            <sch:seqNumber>9</sch:seqNumber>
            <sch:displayValue>产品详情logo图片</sch:displayValue>
            <sch:dataValue>LOGOIMG</sch:dataValue>
            <sch:keyValues>{}</sch:keyValues>
        </sch:BmfDomainEntry>
    </sch:domainEntries>
</sch:DomainTable>